<?xml version="1.0" encoding="UTF-8"?>  
<!DOCTYPE plist PUBLIC "-//Apple//DTD PLIST 1.0//EN" "http://www.apple.com/DTDs/PropertyList-1.0.dtd">  
<plist version="1.0">  
  <dict>  
    <key>MODE_SELECT</key>
    <string>模式选择</string>
    <key>GOBACK</key>
    <string>返回</string>
	<key>RANDOM_JOIN</key>
	<string>随机加入</string>
	<key>FIND_PLAYER</key>
	<string>查找玩家</string>
	<key>XX_GAMEMODE</key>
	<string>XX模式</string>
	<key>FIND_ROOM</key>
	<string>查找房间</string>
	<key>CREATE_ROOM</key>
	<string>创建房间</string>
	<key>INPUT_PLAYER_ID</key>
	<string>请输入玩家ID:</string>
	<key>INPUT_ROOM_ID</key>
	<string>请输入房间ID</string>
	<key>BUTTON_OK</key>
	<string>确定</string>
	<key>BUTTON_CANCEL</key>
	<string>取消</string>
	<key>ROOM_NAME</key>
	<string>房间名称</string>
	<key>ROOM_PASSWORD</key>
	<string>房间密码</string>
	<key>ROOM_ID</key>
	<string>房间ID</string>
	<key>FIGHT_PLAYER_NUM</key>
	<string>对战人数</string>
	<key>PLAY_GAME_MODE</key>
	<string>撮合方式</string>
	<key>RANDOM</key>
	<string>随机</string>
	<key>FREEDOM</key>
	<string>自由</string>
	<key>INVITE_PLAYER</key>
	<string>邀请</string>
	<key>FIGHT_PROPS</key>
	<string>战斗道具</string>
	<key>GETREADGAME</key>
	<string>准备游戏</string>
	<key>SOUL_SETTING</key>
	<string>魂魄调整</string>
	<key>SELECT_MAP</key>
	<string>选择地图</string>
	<key>FRIEND</key>
	<string>好友</string>
	<key>SOCIETIES</key>
	<string>社团</string>
	<key>PLAYER_INLINE</key>
	<string>在线玩家</string>
	<key>BAG</key>
	<string>背包</string>
	<key>PROPS_BUY</key>
	<string>购买道具</string>
	<key>TITLE_SELECT_MAP</key>
	<string>地图选择:</string>
	<key>RECOMMEND_LEVEL</key>
	<string>推荐等级:</string>
	<key>COMSUME_STRENGTH</key>
	<string>消耗体力:</string>
	<key>LIMIT_TIMES</key>
	<string>次数限制:</string>
	<key>REWARDS</key>
	<string>奖励:</string>
	<key>EXPERIENCE</key>
	<string>经验值</string>
	<key>GOLD</key>
	<string>元宝</string>
	<key>MONEY</key>
	<string>铜钱</string>
	<key>CREATE_TEAM</key>
	<string>创建队伍</string>
	<key>SEARCH_TEAM</key>
	<string>搜索队伍</string>
	<key>FAST_JOIN</key>
	<string>快速加入</string>
	<key>TEAM_ID</key>
	<string>队伍号码</string>
	<key>SEARCHING</key>
	<string>搜索</string>
	<key>TOJOIN</key>
	<string>加入</string>
	<key>TEAM_NAME</key>
	<string>队伍名称</string>
	<key>TEAM_PASSWORD</key>
	<string>队伍密码</string>
	<key>BUTTON_CREATE</key>
	<string>创建</string>
	<key>SEARCH_RESULT</key>
	<string>搜索结果</string>
	<key>TEAM_ID</key>
	<string>队伍号码</string>
	<key>PLAYER_NUM</key>
	<string>人数</string>
	<key>PLAYER_LEVEL</key>
	<string>玩家等级</string>
	<key>PLAYER_NICKNAME</key>
	<string>玩家昵称</string>
	<key>COMBAT_POWER</key>
	<string>战斗力</string>
	<key>LEVELS</key>
	<string>关卡</string>
	<key>PLACE_NAME</key>
	<string>地点名称</string>
	<key>OBSERVE_FIGHT</key>
	<string>观摩</string>
	<key>FIGHTING</key>
	<string>战斗</string>
	<key>PVE_FIGHT_FLOP</key>
	<string>战斗翻牌</string>
	<key>FLOP_FREE</key>
	<string>免费翻牌:</string>
	<key>FLOP_GOLD</key>
	<string>金币翻牌:</string>
	<key>START_GAME</key>
	<string>开始</string>
	<key>FIGHT_OVER</key>
	<string>战斗结束</string>
	<key>CLUB_STNC</key>
	<string>社团昵称</string>
	<key>CLUB_QBST</key>
	<string>全部社团</string>
	<key>CLUB_TZNC</key>
	<string>团长昵称</string>
	<key>CLUB_DJ</key>
	<string>等级</string>
	<key>CLUB_RS</key>
	<string>人数</string>
	<key>CLUB_YSQ</key>
	<string>已申请</string>
	<key>CLUB_JR</key>
	<string>加入</string>
	<key>CLUB_SS</key>
	<string>搜索</string>
	<key>CLUB_KC</key>
	<string>开除</string>
	<key>CLUB_TZ</key>
	<string>挑战</string>
	<key>CLUB_JJ</key>
	<string>简介</string>
	<key>CLUB_CY</key>
	<string>成员</string>
	<key>CLUB_CYNC</key>
	<string>成员昵称</string>
	<key>CLUB_ZWM</key>
	<string>职位名</string>
	<key>CLUB_ZT</key>
	<string>状态</string>
	<key>CLUB_XX</key>
	<string>详细</string>
	<key>CLUB_YQ</key>
	<string>邀请</string>
	<key>CLUB_HY</key>
	<string>好友</string>
	<key>CLUB_TY</key>
	<string>同意</string>
	<key>CLUB_JUJUE</key>
	<string>拒绝</string>
	<key>CLUB_SGJH</key>
	<string>上官金鸿</string>
	<key>CLUB_ZJLX</key>
	<string>最近联系</string>
	<key>CLUB_LQ</key>
	<string>领取</string>
	<key>CLUB_HF</key>
	<string>回复</string>
	<key>CLUB_FS</key>
	<string>发送</string>
	<key>CLUB_DQ</key>
	<string>当前</string>
	<key>FIGHT_CURRENTPLAYER</key>
	<string>当前:</string>
	<key>FIGHT_NEXTPLAYER</key>
	<string>次位:</string>
	<key>TJP_QH</key>
	<string>强化</string>
	<key>TJP_XQ</key>
	<string>镶嵌</string>
  </dict>  
</plist>  